madokami/__init__.py
madokami/api/__init__.py
madokami/api/app.py
madokami/api/downloads.py
madokami/api/engines.py
madokami/api/logs.py
madokami/api/media.py
madokami/api/models.py
madokami/api/plugins.py
madokami/api/register.py
madokami/api/scheduler.py
madokami/api/settings.py
madokami/api/subscribe.py
madokami/api/utils.py
madokami/app.py
madokami/config.py
madokami/crud.py
madokami/db.py
madokami/drivers/__init__.py
madokami/drivers/app.py
madokami/drivers/deps.py
madokami/drivers/hooks.py
madokami/drivers/madokami.py
madokami/drivers/router.py
madokami/internal/__init__.py
madokami/internal/core_config.py
madokami/internal/default_plugins/__init__.py
madokami/internal/default_plugins/bangumi_requester.py
madokami/internal/default_plugins/default_downloader.py
madokami/internal/default_plugins/default_requester.py
madokami/internal/downloader.py
madokami/internal/models.py
madokami/internal/scheduler.py
madokami/internal/settings.py
madokami/internal/utils.py
madokami/log.py
madokami/models.py
madokami/plugin/__init__.py
madokami/plugin/backend/__init__.py
madokami/plugin/backend/downloader.py
madokami/plugin/backend/engine.py
madokami/plugin/backend/models.py
madokami/plugin/backend/parser.py
madokami/plugin/backend/requester.py
madokami/plugin/basic_plugin.py
madokami/plugin/engine_register.py
madokami/plugin/hooks.py
madokami/plugin/manager.py
madokami/plugin/models.py
madokami/plugin/settings_register.py
madokami/plugin/subscription.py
madokami/plugin/subscription_regiser.py
madokami/util.py
madokami-0.1.6.dist-info/WHEEL
madokami-0.1.6.dist-info/METADATA
madokami-0.1.6.dist-info/RECORD
