Metadata-Version: 2.1
Name: madokami
Version: 0.1.6
Summary: A core library for madokami
Author: Hongpei Zheng
Author-email: summerkirakira@gmail.com
Requires-Python: >=3.10,<4.0
Classifier: Programming Language :: Python :: 3
Classifier: Programming Language :: Python :: 3.10
Classifier: Programming Language :: Python :: 3.11
Requires-Dist: apscheduler (>=3.10.4,<4.0.0)
Requires-Dist: aria2p (>=0.12.0,<0.13.0)
Requires-Dist: fastapi (>=0.110.1,<0.111.0)
Requires-Dist: loguru (>=0.7.2,<0.8.0)
Requires-Dist: pydantic (>=2.7.0,<3.0.0)
Requires-Dist: pytest (>=8.1.1,<9.0.0)
Requires-Dist: pytest-xdist (>=3.5.0,<4.0.0)
Requires-Dist: pyyaml (>=6.0.1,<7.0.0)
Requires-Dist: requests (>=2.31.0,<3.0.0)
Requires-Dist: sqlalchemy (>=2.0.29,<3.0.0)
Requires-Dist: sqlmodel (>=0.0.16,<0.0.17)
Requires-Dist: uvicorn (>=0.29.0,<0.30.0)
Requires-Dist: yt-dlp (>=2024.4.9,<2025.0.0)
